[
  {
    "id": 1,
    "nombre": "Finland",
    "categoria": "Western Europe",
    "valor": 7.804,
    "fecha": "2023-03-20",
    "country": "Finland",
    "regional_indicator": "Western Europe",
    "happiness_score": 7.804,
    "log_gdp_per_capita": 11.30,
    "social_support": 0.954,
    "healthy_life_expectancy": 71.9,
    "freedom_to_make_choices": 0.949,
    "generosity": 0.142,
    "perceptions_of_corruption": 0.179
  },
  {
    "id": 2,
    "nombre": "Denmark",
    "categoria": "Western Europe",
    "valor": 7.586,
    "fecha": "2023-03-20",
    "country": "Denmark",
    "regional_indicator": "Western Europe",
    "happiness_score": 7.586,
    "log_gdp_per_capita": 11.38,
    "social_support": 0.954,
    "healthy_life_expectancy": 72.0,
    "freedom_to_make_choices": 0.946,
    "generosity": 0.283,
    "perceptions_of_corruption": 0.170
  },
  {
    "id": 3,
    "nombre": "Iceland",
    "categoria": "Western Europe",
    "valor": 7.530,
    "fecha": "2023-03-20",
    "country": "Iceland",
    "regional_indicator": "Western Europe",
    "happiness_score": 7.530,
    "log_gdp_per_capita": 11.29,
    "social_support": 0.983,
    "healthy_life_expectancy": 73.0,
    "freedom_to_make_choices": 0.908,
    "generosity": 0.259,
    "perceptions_of_corruption": 0.673
  },
  {
    "id": 4,
    "nombre": "Israel",
    "categoria": "Middle East and North Africa",
    "valor": 7.473,
    "fecha": "2023-03-20",
    "country": "Israel",
    "regional_indicator": "Middle East and North Africa",
    "happiness_score": 7.473,
    "log_gdp_per_capita": 10.98,
    "social_support": 0.930,
    "healthy_life_expectancy": 72.4,
    "freedom_to_make_choices": 0.838,
    "generosity": 0.168,
    "perceptions_of_corruption": 0.801
  },
  {
    "id": 5,
    "nombre": "Netherlands",
    "categoria": "Western Europe",
    "valor": 7.403,
    "fecha": "2023-03-20",
    "country": "Netherlands",
    "regional_indicator": "Western Europe",
    "happiness_score": 7.403,
    "log_gdp_per_capita": 11.22,
    "social_support": 0.942,
    "healthy_life_expectancy": 72.2,
    "freedom_to_make_choices": 0.913,
    "generosity": 0.241,
    "perceptions_of_corruption": 0.338
  },
  {
    "id": 6,
    "nombre": "Sweden",
    "categoria": "Western Europe",
    "valor": 7.395,
    "fecha": "2023-03-20",
    "country": "Sweden",
    "regional_indicator": "Western Europe",
    "happiness_score": 7.395,
    "log_gdp_per_capita": 11.18,
    "social_support": 0.934,
    "healthy_life_expectancy": 72.9,
    "freedom_to_make_choices": 0.938,
    "generosity": 0.221,
    "perceptions_of_corruption": 0.224
  },
  {
    "id": 7,
    "nombre": "Norway",
    "categoria": "Western Europe",
    "valor": 7.315,
    "fecha": "2023-03-20",
    "country": "Norway",
    "regional_indicator": "Western Europe",
    "happiness_score": 7.315,
    "log_gdp_per_capita": 11.47,
    "social_support": 0.954,
    "healthy_life_expectancy": 73.3,
    "freedom_to_make_choices": 0.955,
    "generosity": 0.243,
    "perceptions_of_corruption": 0.282
  },
  {
    "id": 8,
    "nombre": "Switzerland",
    "categoria": "Western Europe",
    "valor": 7.240,
    "fecha": "2023-03-20",
    "country": "Switzerland",
    "regional_indicator": "Western Europe",
    "happiness_score": 7.240,
    "log_gdp_per_capita": 11.59,
    "social_support": 0.942,
    "healthy_life_expectancy": 74.1,
    "freedom_to_make_choices": 0.921,
    "generosity": 0.275,
    "perceptions_of_corruption": 0.363
  },
  {
    "id": 9,
    "nombre": "Luxembourg",
    "categoria": "Western Europe",
    "valor": 7.228,
    "fecha": "2023-03-20",
    "country": "Luxembourg",
    "regional_indicator": "Western Europe",
    "happiness_score": 7.228,
    "log_gdp_per_capita": 11.92,
    "social_support": 0.906,
    "healthy_life_expectancy": 72.4,
    "freedom_to_make_choices": 0.910,
    "generosity": 0.231,
    "perceptions_of_corruption": 0.371
  },
  {
    "id": 10,
    "nombre": "New Zealand",
    "categoria": "ANZ",
    "valor": 7.123,
    "fecha": "2023-03-20",
    "country": "New Zealand",
    "regional_indicator": "ANZ",
    "happiness_score": 7.123,
    "log_gdp_per_capita": 10.87,
    "social_support": 0.944,
    "healthy_life_expectancy": 73.0,
    "freedom_to_make_choices": 0.929,
    "generosity": 0.320,
    "perceptions_of_corruption": 0.415
  },
  {
    "id": 11,
    "nombre": "Austria",
    "categoria": "Western Europe",
    "valor": 7.097,
    "fecha": "2023-03-20",
    "country": "Austria",
    "regional_indicator": "Western Europe",
    "happiness_score": 7.097,
    "log_gdp_per_capita": 11.18,
    "social_support": 0.927,
    "healthy_life_expectancy": 73.3,
    "freedom_to_make_choices": 0.904,
    "generosity": 0.194,
    "perceptions_of_corruption": 0.538
  },
  {
    "id": 12,
    "nombre": "Australia",
    "categoria": "ANZ",
    "valor": 7.095,
    "fecha": "2023-03-20",
    "country": "Australia",
    "regional_indicator": "ANZ",
    "happiness_score": 7.095,
    "log_gdp_per_capita": 11.09,
    "social_support": 0.944,
    "healthy_life_expectancy": 73.8,
    "freedom_to_make_choices": 0.917,
    "generosity": 0.310,
    "perceptions_of_corruption": 0.467
  },
  {
    "id": 13,
    "nombre": "Canada",
    "categoria": "North America and ANZ",
    "valor": 6.961,
    "fecha": "2023-03-20",
    "country": "Canada",
    "regional_indicator": "North America and ANZ",
    "happiness_score": 6.961,
    "log_gdp_per_capita": 11.08,
    "social_support": 0.935,
    "healthy_life_expectancy": 73.6,
    "freedom_to_make_choices": 0.897,
    "generosity": 0.226,
    "perceptions_of_corruption": 0.518
  },
  {
    "id": 14,
    "nombre": "Ireland",
    "categoria": "Western Europe",
    "valor": 6.911,
    "fecha": "2023-03-20",
    "country": "Ireland",
    "regional_indicator": "Western Europe",
    "happiness_score": 6.911,
    "log_gdp_per_capita": 11.59,
    "social_support": 0.928,
    "healthy_life_expectancy": 72.3,
    "freedom_to_make_choices": 0.923,
    "generosity": 0.268,
    "perceptions_of_corruption": 0.444
  },
  {
    "id": 15,
    "nombre": "United States",
    "categoria": "North America and ANZ",
    "valor": 6.894,
    "fecha": "2023-03-20",
    "country": "United States",
    "regional_indicator": "North America and ANZ",
    "happiness_score": 6.894,
    "log_gdp_per_capita": 11.38,
    "social_support": 0.899,
    "healthy_life_expectancy": 68.3,
    "freedom_to_make_choices": 0.842,
    "generosity": 0.246,
    "perceptions_of_corruption": 0.681
  },
  {
    "id": 16,
    "nombre": "Germany",
    "categoria": "Western Europe",
    "valor": 6.892,
    "fecha": "2023-03-20",
    "country": "Germany",
    "regional_indicator": "Western Europe",
    "happiness_score": 6.892,
    "log_gdp_per_capita": 11.17,
    "social_support": 0.908,
    "healthy_life_expectancy": 72.6,
    "freedom_to_make_choices": 0.911,
    "generosity": 0.203,
    "perceptions_of_corruption": 0.485
  },
  {
    "id": 17,
    "nombre": "Belgium",
    "categoria": "Western Europe",
    "valor": 6.859,
    "fecha": "2023-03-20",
    "country": "Belgium",
    "regional_indicator": "Western Europe",
    "happiness_score": 6.859,
    "log_gdp_per_capita": 11.09,
    "social_support": 0.920,
    "healthy_life_expectancy": 72.0,
    "freedom_to_make_choices": 0.876,
    "generosity": 0.149,
    "perceptions_of_corruption": 0.627
  },
  {
    "id": 18,
    "nombre": "Czechia",
    "categoria": "Central and Eastern Europe",
    "valor": 6.845,
    "fecha": "2023-03-20",
    "country": "Czechia",
    "regional_indicator": "Central and Eastern Europe",
    "happiness_score": 6.845,
    "log_gdp_per_capita": 10.82,
    "social_support": 0.928,
    "healthy_life_expectancy": 70.1,
    "freedom_to_make_choices": 0.880,
    "generosity": 0.062,
    "perceptions_of_corruption": 0.793
  },
  {
    "id": 19,
    "nombre": "United Kingdom",
    "categoria": "Western Europe",
    "valor": 6.796,
    "fecha": "2023-03-20",
    "country": "United Kingdom",
    "regional_indicator": "Western Europe",
    "happiness_score": 6.796,
    "log_gdp_per_capita": 10.97,
    "social_support": 0.914,
    "healthy_life_expectancy": 72.0,
    "freedom_to_make_choices": 0.879,
    "generosity": 0.305,
    "perceptions_of_corruption": 0.557
  },
  {
    "id": 20,
    "nombre": "Lithuania",
    "categoria": "Central and Eastern Europe",
    "valor": 6.763,
    "fecha": "2023-03-20",
    "country": "Lithuania",
    "regional_indicator": "Central and Eastern Europe",
    "happiness_score": 6.763,
    "log_gdp_per_capita": 10.85,
    "social_support": 0.892,
    "healthy_life_expectancy": 68.0,
    "freedom_to_make_choices": 0.862,
    "generosity": 0.038,
    "perceptions_of_corruption": 0.841
  },
  {
    "id": 21,
    "nombre": "France",
    "categoria": "Western Europe",
    "valor": 6.661,
    "fecha": "2023-03-20",
    "country": "France",
    "regional_indicator": "Western Europe",
    "happiness_score": 6.661,
    "log_gdp_per_capita": 10.99,
    "social_support": 0.901,
    "healthy_life_expectancy": 73.6,
    "freedom_to_make_choices": 0.828,
    "generosity": 0.111,
    "perceptions_of_corruption": 0.774
  },
  {
    "id": 22,
    "nombre": "Slovenia",
    "categoria": "Central and Eastern Europe",
    "valor": 6.650,
    "fecha": "2023-03-20",
    "country": "Slovenia",
    "regional_indicator": "Central and Eastern Europe",
    "happiness_score": 6.650,
    "log_gdp_per_capita": 10.83,
    "social_support": 0.933,
    "healthy_life_expectancy": 73.0,
    "freedom_to_make_choices": 0.850,
    "generosity": 0.111,
    "perceptions_of_corruption": 0.859
  },
  {
    "id": 23,
    "nombre": "Costa Rica",
    "categoria": "Latin America and Caribbean",
    "valor": 6.609,
    "fecha": "2023-03-20",
    "country": "Costa Rica",
    "regional_indicator": "Latin America and Caribbean",
    "happiness_score": 6.609,
    "log_gdp_per_capita": 10.10,
    "social_support": 0.898,
    "healthy_life_expectancy": 71.2,
    "freedom_to_make_choices": 0.865,
    "generosity": 0.148,
    "perceptions_of_corruption": 0.803
  },
  {
    "id": 24,
    "nombre": "Chile",
    "categoria": "Latin America and Caribbean",
    "valor": 6.587,
    "fecha": "2023-03-20",
    "country": "Chile",
    "regional_indicator": "Latin America and Caribbean",
    "happiness_score": 6.587,
    "log_gdp_per_capita": 10.51,
    "social_support": 0.890,
    "healthy_life_expectancy": 71.0,
    "freedom_to_make_choices": 0.819,
    "generosity": 0.096,
    "perceptions_of_corruption": 0.860
  },
  {
    "id": 25,
    "nombre": "Panama",
    "categoria": "Latin America and Caribbean",
    "valor": 6.524,
    "fecha": "2023-03-20",
    "country": "Panama",
    "regional_indicator": "Latin America and Caribbean",
    "happiness_score": 6.524,
    "log_gdp_per_capita": 10.46,
    "social_support": 0.870,
    "healthy_life_expectancy": 70.5,
    "freedom_to_make_choices": 0.847,
    "generosity": 0.159,
    "perceptions_of_corruption": 0.847
  },
  {
    "id": 26,
    "nombre": "Mexico",
    "categoria": "Latin America and Caribbean",
    "valor": 6.330,
    "fecha": "2023-03-20",
    "country": "Mexico",
    "regional_indicator": "Latin America and Caribbean",
    "happiness_score": 6.330,
    "log_gdp_per_capita": 10.28,
    "social_support": 0.867,
    "healthy_life_expectancy": 68.2,
    "freedom_to_make_choices": 0.829,
    "generosity": 0.091,
    "perceptions_of_corruption": 0.887
  },
  {
    "id": 27,
    "nombre": "Uruguay",
    "categoria": "Latin America and Caribbean",
    "valor": 6.273,
    "fecha": "2023-03-20",
    "country": "Uruguay",
    "regional_indicator": "Latin America and Caribbean",
    "happiness_score": 6.273,
    "log_gdp_per_capita": 10.40,
    "social_support": 0.921,
    "healthy_life_expectancy": 70.4,
    "freedom_to_make_choices": 0.860,
    "generosity": 0.142,
    "perceptions_of_corruption": 0.878
  },
  {
    "id": 28,
    "nombre": "Brazil",
    "categoria": "Latin America and Caribbean",
    "valor": 6.125,
    "fecha": "2023-03-20",
    "country": "Brazil",
    "regional_indicator": "Latin America and Caribbean",
    "happiness_score": 6.125,
    "log_gdp_per_capita": 10.11,
    "social_support": 0.855,
    "healthy_life_expectancy": 66.8,
    "freedom_to_make_choices": 0.810,
    "generosity": 0.147,
    "perceptions_of_corruption": 0.900
  },
  {
    "id": 29,
    "nombre": "Argentina",
    "categoria": "Latin America and Caribbean",
    "valor": 6.096,
    "fecha": "2023-03-20",
    "country": "Argentina",
    "regional_indicator": "Latin America and Caribbean",
    "happiness_score": 6.096,
    "log_gdp_per_capita": 10.21,
    "social_support": 0.900,
    "healthy_life_expectancy": 68.8,
    "freedom_to_make_choices": 0.812,
    "generosity": 0.112,
    "perceptions_of_corruption": 0.878
  },
  {
    "id": 30,
    "nombre": "Colombia",
    "categoria": "Latin America and Caribbean",
    "valor": 6.057,
    "fecha": "2023-03-20",
    "country": "Colombia",
    "regional_indicator": "Latin America and Caribbean",
    "happiness_score": 6.057,
    "log_gdp_per_capita": 10.02,
    "social_support": 0.854,
    "healthy_life_expectancy": 68.4,
    "freedom_to_make_choices": 0.835,
    "generosity": 0.143,
    "perceptions_of_corruption": 0.893
  }
]
